ifixit2zim/__about__.py
ifixit2zim/__init__.py
ifixit2zim/__main__.py
ifixit2zim/constants.py
ifixit2zim/context.py
ifixit2zim/entrypoint.py
ifixit2zim/exceptions.py
ifixit2zim/executor.py
ifixit2zim/imager.py
ifixit2zim/processor.py
ifixit2zim/scraper.py
ifixit2zim/scraper_category.py
ifixit2zim/scraper_generic.py
ifixit2zim/scraper_guide.py
ifixit2zim/scraper_homepage.py
ifixit2zim/scraper_info.py
ifixit2zim/scraper_user.py
ifixit2zim/shared.py
ifixit2zim/utils.py
ifixit2zim/assets/16px_11px_5.png
ifixit2zim/assets/32px_32px_5.png
ifixit2zim/assets/FrameModules-translation_credit-qBLVoFL8fSDpJmDUuduPTA.css
ifixit2zim/assets/GuideNoImage_300x225.jpg
ifixit2zim/assets/NoImage_300x225.jpg
ifixit2zim/assets/NoImage_56x42.jpg
ifixit2zim/assets/NoImage_96x72.jpg
ifixit2zim/assets/PIE.htc
ifixit2zim/assets/S6u8w4BMUTPHjxsAUi-qNiXg7eU0.woff2
ifixit2zim/assets/S6u8w4BMUTPHjxsAXC-qNiXg7Q.woff2
ifixit2zim/assets/S6u9w4BMUTPHh6UVSwaPGQ3q5d0N7w.woff2
ifixit2zim/assets/S6u9w4BMUTPHh6UVSwiPGQ3q5d0.woff2
ifixit2zim/assets/S6uyw4BMUTPHjx4wXiWtFCc.woff2
ifixit2zim/assets/S6uyw4BMUTPHjxAwXiWtFCfQ7A.woff2
ifixit2zim/assets/Shared-attachment_link-AoWbgS-g65jo1DYOaHV5XA.css
ifixit2zim/assets/Shared-cart_banner-33Ctp6kCy0R-IiTsFeV6cw.css
ifixit2zim/assets/Shared-i18n_formatting-7XRaMqur0Z-hJvP-W8sS2A.css
ifixit2zim/assets/Shared-print-ej-m-RsicBzcpqbxdfzumQ.css
ifixit2zim/assets/Wiki-common-Zf5O-KLmFhhZ0w9cRZYZoQ.css
ifixit2zim/assets/Wiki-topic-r_spN9srKqcGQAC8emdeTA.css
ifixit2zim/assets/area_index-BDTBciD-Y7NVVjoPQBUyhA.css
ifixit2zim/assets/badge_icons_20110608.png
ifixit2zim/assets/camera-large-add-2.png
ifixit2zim/assets/camera-small-add-2.png
ifixit2zim/assets/check1x.png
ifixit2zim/assets/check2x.png
ifixit2zim/assets/checklarge1x.png
ifixit2zim/assets/checklarge2x.png
ifixit2zim/assets/checksmall1x.png
ifixit2zim/assets/checksmall2x.png
ifixit2zim/assets/core-ETWCjfemWxBbJHaoXafxFg.css
ifixit2zim/assets/core-primitives-F5WnAWhrwpl7oCtqtgogQQ.css
ifixit2zim/assets/css2.css
ifixit2zim-0.3.1.dist-info/METADATA
ifixit2zim-0.3.1.dist-info/WHEEL
ifixit2zim-0.3.1.dist-info/entry_points.txt
ifixit2zim-0.3.1.dist-info/licenses/LICENSE
ifixit2zim-0.3.1.dist-info/RECORD
