Metadata-Version: 2.1
Name: ifixit2zim
Version: 0.3.1
Summary: Make ZIM file from iFixit guides
Project-URL: Homepage, https://github.com/openzim/ifixit2zim
Project-URL: Donate, https://www.kiwix.org/en/support-us/
Author-email: Kiwix <dev@kiwix.org>
License: GPL-3.0-or-later
License-File: LICENSE
Keywords: ifixit,kiwix,offline,zim
Classifier: License :: OSI Approved :: GNU General Public License v3 or later (GPLv3+)
Classifier: Programming Language :: Python :: 3
Classifier: Programming Language :: Python :: 3.12
Requires-Python: <3.13,>=3.12
Requires-Dist: backoff==2.2.1
Requires-Dist: jinja2==3.1.3
Requires-Dist: kiwixstorage==0.8.3
Requires-Dist: pif==0.8.2
Requires-Dist: requests==2.31.0
Requires-Dist: schedule==1.2.1
Requires-Dist: zimscraperlib==3.3.1
Provides-Extra: check
Requires-Dist: pyright==1.1.352; extra == 'check'
Provides-Extra: dev
Requires-Dist: debugpy==1.8.1; extra == 'dev'
Requires-Dist: ifixit2zim[check]; extra == 'dev'
Requires-Dist: ifixit2zim[lint]; extra == 'dev'
Requires-Dist: ifixit2zim[scripts]; extra == 'dev'
Requires-Dist: ifixit2zim[test]; extra == 'dev'
Requires-Dist: pre-commit==3.6.2; extra == 'dev'
Provides-Extra: lint
Requires-Dist: black==24.2.0; extra == 'lint'
Requires-Dist: ruff==0.3.0; extra == 'lint'
Provides-Extra: scripts
Requires-Dist: invoke==2.2.0; extra == 'scripts'
Provides-Extra: test
Requires-Dist: coverage==7.4.3; extra == 'test'
Requires-Dist: pytest==8.0.2; extra == 'test'
